geovizpy/__init__.py
geovizpy/controls.py
geovizpy/effects.py
geovizpy/geoviz.py
geovizpy/legends.py
geovizpy/marks.py
geovizpy/plots.py
geovizpy/renderer.py
geovizpy-0.1.6.dist-info/METADATA
geovizpy-0.1.6.dist-info/WHEEL
geovizpy-0.1.6.dist-info/top_level.txt
geovizpy-0.1.6.dist-info/RECORD
