Metadata-Version: 2.4
Name: geovizpy
Version: 0.1.6
Summary: A Python wrapper for the geoviz JavaScript library
Author: fbxyz
Project-URL: Source, https://codeberg.org/fbxyz/geovizpy
Classifier: Programming Language :: Python :: 3
Classifier: License :: OSI Approved :: MIT License
Classifier: Operating System :: OS Independent
Requires-Python: >=3.6
Provides-Extra: export
Requires-Dist: playwright; extra == "export"
Dynamic: author
Dynamic: classifier
Dynamic: description
Dynamic: description-content-type
Dynamic: project-url
Dynamic: provides-extra
Dynamic: requires-python
Dynamic: summary
